vape/__init__.py
vape-0.1.1.dist-info/DESCRIPTION.rst
vape-0.1.1.dist-info/METADATA
vape-0.1.1.dist-info/RECORD
vape-0.1.1.dist-info/WHEEL
vape-0.1.1.dist-info/entry_points.txt
vape-0.1.1.dist-info/metadata.json
vape-0.1.1.dist-info/top_level.txt
