Metadata-Version: 2.0
Name: vape
Version: 0.1.1
Summary: Command line aesthetic generator.
Home-page: https://github.com/Miserlou/Vape
Author: Rich Jones
Author-email: rich@openwatch.net
License: MIT License
Platform: UNKNOWN
Classifier: Environment :: Console
Classifier: License :: OSI Approved :: Apache Software License
Classifier: Operating System :: OS Independent
Classifier: Programming Language :: Python
Classifier: Programming Language :: Python :: 2.6
Classifier: Programming Language :: Python :: 2.7
Classifier: Topic :: Internet :: WWW/HTTP
Classifier: Topic :: Internet :: WWW/HTTP :: Dynamic Content
Requires-Dist: appdirs (==1.4.3)
Requires-Dist: packaging (==16.8)
Requires-Dist: pyparsing (==2.2.0)
Requires-Dist: six (==1.10.0)
Requires-Dist: xerox (==0.4.1)
